neuro_maintenance_checker/__init__.py
neuro_maintenance_checker/py.typed
tests/__init__.py
tests/conftest.py
tests/test_poller.py
neuro_maintenance_checker-22.2.2.dist-info/LICENSE
neuro_maintenance_checker-22.2.2.dist-info/METADATA
neuro_maintenance_checker-22.2.2.dist-info/WHEEL
neuro_maintenance_checker-22.2.2.dist-info/top_level.txt
neuro_maintenance_checker-22.2.2.dist-info/RECORD
