Metadata-Version: 2.1
Name: neuro-maintenance-checker
Version: 22.2.2
Summary: Internal service for checking for Neu.ro maintenance mode
Home-page: https://github.com/neuro-inc/neuro-maintenance-checker
License: Apache 2
Platform: UNKNOWN
Classifier: License :: OSI Approved :: Apache Software License
Classifier: Programming Language :: Python :: 3
Requires-Python: >=3.9
License-File: LICENSE
Requires-Dist: aiohttp (>=3.8.1)
Requires-Dist: neuro-config-client (>=22.2.0a0)
Requires-Dist: neuro-admin-client (>=22.2.1)
